pynamodbplus/__init__.py
pynamodbplus/attributes.py
pynamodbplus/models.py
pynamodb_plus-0.0.4.dist-info/LICENSE
pynamodb_plus-0.0.4.dist-info/METADATA
pynamodb_plus-0.0.4.dist-info/WHEEL
pynamodb_plus-0.0.4.dist-info/top_level.txt
pynamodb_plus-0.0.4.dist-info/RECORD
